kostalpyko/__init__.py
kostalpyko/kostalpyko.py
tests/__init__.py
tests/test_kostalpyko.py
kostalpyko-0.5.dist-info/LICENSE.txt
kostalpyko-0.5.dist-info/METADATA
kostalpyko-0.5.dist-info/WHEEL
kostalpyko-0.5.dist-info/top_level.txt
kostalpyko-0.5.dist-info/RECORD
