Metadata-Version: 2.1
Name: kostalpyko
Version: 0.5
Summary: A package for working with a Piko Inverter from Kostal
Home-page: https://github.com/gieljnssns/KostalPikoPy
Author: Giel Janssens
Author-email: gieljnssns@vivaldi.net
License: MIT
Platform: UNKNOWN
Requires-Dist: lxml
